beautifulspoon/__init__.py
beautifulspoon/cli.py
beautifulspoon-0.0.4.dist-info/METADATA
beautifulspoon-0.0.4.dist-info/WHEEL
beautifulspoon-0.0.4.dist-info/entry_points.txt
beautifulspoon-0.0.4.dist-info/RECORD
