Metadata-Version: 2.1
Name: beautifulspoon
Version: 0.0.4
Summary: 
Home-page: https://github.com/gzttech/beautifulspoon
License: MIT
Author: Gongziting Tech Ltd.
Requires-Python: >=3.6.8,<4.0.0
Classifier: License :: OSI Approved :: MIT License
Classifier: Programming Language :: Python :: 3
Classifier: Programming Language :: Python :: 3.7
Classifier: Programming Language :: Python :: 3.8
Classifier: Programming Language :: Python :: 3.9
Classifier: Programming Language :: Python :: 3.10
Classifier: Programming Language :: Python :: 3.11
Classifier: Programming Language :: Python :: 3.12
Requires-Dist: beautifulsoup4 (>=4.10,<5.0)
